kutils4pygame/__init__.py
kutils4pygame/pkg_utils.py
kutils4pygame/test/__init__.py
kutils4pygame-0.1.dist-info/METADATA
kutils4pygame-0.1.dist-info/RECORD
kutils4pygame-0.1.dist-info/WHEEL
kutils4pygame-0.1.dist-info/top_level.txt
